dqops/__init__.py
dqops/__main__.py
dqops/install.py
dqops/py.typed
dqops/startdqo.py
dqops/version.py
dqops/client/__init__.py
dqops/client/client.py
dqops/client/errors.py
dqops/client/py.typed
dqops/client/types.py
dqops/client/api/__init__.py
dqops/client/api/check_results/__init__.py
dqops/client/api/check_results/get_column_monitoring_checks_results.py
dqops/client/api/check_results/get_column_partitioned_checks_results.py
dqops/client/api/check_results/get_column_profiling_checks_results.py
dqops/client/api/check_results/get_table_data_quality_status.py
dqops/client/api/check_results/get_table_issues_histogram.py
dqops/client/api/check_results/get_table_monitoring_checks_results.py
dqops/client/api/check_results/get_table_partitioned_checks_results.py
dqops/client/api/check_results/get_table_profiling_checks_results.py
dqops/client/api/check_results_overview/__init__.py
dqops/client/api/check_results_overview/get_column_monitoring_checks_overview.py
dqops/client/api/check_results_overview/get_column_partitioned_checks_overview.py
dqops/client/api/check_results_overview/get_column_profiling_checks_overview.py
dqops/client/api/check_results_overview/get_table_monitoring_checks_overview.py
dqops/client/api/check_results_overview/get_table_partitioned_checks_overview.py
dqops/client/api/check_results_overview/get_table_profiling_checks_overview.py
dqops/client/api/checks/__init__.py
dqops/client/api/checks/create_check.py
dqops/client/api/checks/delete_check.py
dqops/client/api/checks/get_all_checks.py
dqops/client/api/checks/get_check.py
dqops/client/api/checks/get_check_folder_tree.py
dqops/client/api/checks/update_check.py
dqops/client/api/column_quality_policies/__init__.py
dqops/client/api/column_quality_policies/copy_from_column_quality_policy.py
dqops/client/api/column_quality_policies/create_column_quality_policy.py
dqops/client/api/column_quality_policies/create_column_quality_policy_target.py
dqops-1.13.1.dist-info/licenses/LICENSE
dqops-1.13.1.dist-info/METADATA
dqops-1.13.1.dist-info/WHEEL
dqops-1.13.1.dist-info/entry_points.txt
dqops-1.13.1.dist-info/top_level.txt
dqops-1.13.1.dist-info/RECORD
