Metadata-Version: 2.4
Name: dqops
Version: 1.13.1
Summary: DQOps Data Quality Operations Center
Home-page: https://github.com/dqops/dqo/tree/master/distribution/python
Author: DQOps Developers
Author-email: support@dqops.com
License: http://www.apache.org/licenses/LICENSE-2.0
Classifier: Development Status :: 5 - Production/Stable
Classifier: License :: OSI Approved :: Apache Software License
Classifier: Programming Language :: Python :: 3.8
Classifier: Programming Language :: Python :: 3.9
Classifier: Programming Language :: Python :: 3.10
Classifier: Programming Language :: Python :: 3.11
Classifier: Programming Language :: Python :: 3.12
Classifier: Environment :: Console
Classifier: Framework :: Apache Airflow :: Provider
Classifier: Intended Audience :: Developers
Classifier: Operating System :: Microsoft :: Windows
Classifier: Operating System :: MacOS
Classifier: Operating System :: POSIX :: Linux
Classifier: Programming Language :: Java
Classifier: Programming Language :: SQL
Classifier: Topic :: Database
Classifier: Topic :: Scientific/Engineering :: Artificial Intelligence
Classifier: Topic :: Scientific/Engineering :: Information Analysis
Classifier: Topic :: Security
Classifier: Topic :: Software Development :: Quality Assurance
Classifier: Topic :: Software Development :: Testing
Classifier: Topic :: Software Development :: Version Control :: Git
Classifier: Programming Language :: Python :: Implementation :: CPython
Classifier: Programming Language :: Python :: Implementation :: PyPy
Requires-Python: >=3.8
License-File: LICENSE
Requires-Dist: install-jdk>=1.1.0
Requires-Dist: h2>=4.0.0
Requires-Dist: httpx[http2]>=0.27.0
Requires-Dist: attrs>=21.3.0
Requires-Dist: python-dateutil>=2.8.2
Requires-Dist: numpy>=1.24.3
Requires-Dist: MarkupSafe>=2.1.1
Requires-Dist: Jinja2>=3.0.3
Requires-Dist: six>=1.16.0
Requires-Dist: pandas>=2.0.1
Requires-Dist: scipy>=1.10.1
Dynamic: author
Dynamic: author-email
Dynamic: classifier
Dynamic: description
Dynamic: description-content-type
Dynamic: home-page
Dynamic: license
Dynamic: license-file
Dynamic: requires-dist
Dynamic: requires-python
Dynamic: summary
